castnet/__init__.py
castnet-0.0.10.dist-info/LICENSE
castnet-0.0.10.dist-info/METADATA
castnet-0.0.10.dist-info/WHEEL
castnet-0.0.10.dist-info/top_level.txt
castnet-0.0.10.dist-info/RECORD
