Metadata-Version: 2.1
Name: castnet
Version: 0.0.10
Summary: CastNet is a schema based low level Neo4j connection interaction library your Python back end, enabling easy type conversions and generalized CRUD endpoints (including GraphQL).
Home-page: https://github.com/broadinstitute/castnet
Author: Daniel S. Hitchcock
Author-email: daniel.s.hitchcock@gmail.com
License: MIT
Keywords: Neo4j,REST,graphdb,CRUD,graphql
Platform: UNKNOWN
Classifier: License :: OSI Approved :: MIT License
Classifier: Programming Language :: Python :: 3
License-File: LICENSE
Requires-Dist: neo4j
Requires-Dist: shortuuid
